rtl/alu.sv
module alu (
  input  logic [2:0]  op,          // 000 ADD,001 SUB,010 AND,011 OR,100 XOR,101 SLT
  input  logic [31:0] a, b,
  output logic [31:0] y,
  output logic        z, n, c, v
);
  logic [31:0] res; 
  logic c_int, v_int;

  always @* begin
    c_int = 1'b0; 
    v_int = 1'b0; 
    res   = '0;
    unique case (op)
      3'b000: begin 
        {c_int,res} = a + b; 
        v_int = ((a[31]==b[31]) && (res[31]!=a[31])); 
      end
      3'b001: begin 
        {c_int,res} = a - b; 
        v_int = ((a[31]!=b[31]) && (res[31]!=a[31])); 
      end
      3'b010: res = a & b;
      3'b011: res = a | b;
      3'b100: res = a ^ b;
      3'b101: res = ($signed(a) < $signed(b)) ? 32'd1 : 32'd0;
      default: res = '0;
    endcase

    // Assign outputs
    y = res;
    z = (res == '0);
    n = res[31];
    c = c_int;
    v = v_int;
  end
endmodule

tb/top_tb.sv
`timescale 1ns/1ps
module top_tb;
  logic clk=0; always #5 clk = ~clk;
  logic [2:0]  op;
  logic [31:0] a, b, y;
  logic z, n, c, v;

  alu dut(.op(op), .a(a), .b(b), .y(y), .z(z), .n(n), .c(c), .v(v));

  task do_vec(input [2:0] op_i, input [31:0] a_i, b_i);
    begin op=op_i; a=a_i; b=b_i; @(posedge clk); end
  endtask

  initial begin
    $dumpfile("build/alu.vcd"); $dumpvars(0, top_tb);

    // Directed
    do_vec(3'd0, 32'd2, 32'd3); if (y!==32'd5) $error("ADD failed: %0d", y);
    do_vec(3'd1, 32'd7, 32'd7); if (!z)        $error("SUB zero flag not set");
    do_vec(3'd5, 32'hFFFF_FFFF, 32'd1); if (y!==32'd1) $error("SLT failed");

    // Random
    repeat (2000) begin
      do_vec($urandom%6, $urandom, $urandom);
    end
    $display("CHECK PASS"); $finish;
  end
endmodule

build/alu.vcd
$date
	Sat Oct  4 12:38:28 2025
$end
$version
	Icarus Verilog
$end
$timescale
	1ps
$end
$scope module top_tb $end
$var wire 1 ! z $end
$var wire 32 " y [31:0] $end
$var wire 1 # v $end
$var wire 1 $ n $end
$var wire 1 % c $end
$var reg 32 & a [31:0] $end
$var reg 32 ' b [31:0] $end
$var reg 1 ( clk $end
$var reg 3 ) op [2:0] $end
$scope module dut $end
$var wire 32 * a [31:0] $end
$var wire 32 + b [31:0] $end
$var wire 3 , op [2:0] $end
$var reg 1 % c $end
$var reg 1 - c_int $end
$var reg 1 $ n $end
$var reg 32 . res [31:0] $end
$var reg 1 # v $end
$var reg 1 / v_int $end
$var reg 32 0 y [31:0] $end
$var reg 1 ! z $end
$upscope $end
$scope task do_vec $end
$var reg 32 1 a_i [31:0] $end
$var reg 32 2 b_i [31:0] $end
$var reg 3 3 op_i [2:0] $end
$upscope $end
$upscope $end
$enddefinitions $end
$comment Show the parameter values. $end
$dumpall
$end
#0
$dumpvars
b0 3
b11 2
b10 1
b101 0
0/
b101 .
0-
b0 ,
b11 +
b10 *
b0 )
0(
b11 '
b10 &
0%
0$
0#
b101 "
0!
$end
#5000
1!
b0 "
b0 0
b0 .
b111 '
b111 +
b111 &
b111 *
b1 )
b1 ,
b111 2
b111 1
b1 3
1(
#10000
0(
#15000
0!
b1 "
b1 0
b1 .
b1 '
b1 +
b11111111111111111111111111111111 &
b11111111111111111111111111111111 *
b101 )
b101 ,
b1 2
b11111111111111111111111111111111 1
b101 3
1(
#20000
0(
#25000
b1000100000011011000100010001000 "
b1000100000011011000100010001000 0
b1000100000011011000100010001000 .
b100100001001101011000001001 '
b100100001001101011000001001 +
b1000000100010010101111010000001 &
b1000000100010010101111010000001 *
b100 )
b100 ,
b100100001001101011000001001 2
b1000000100010010101111010000001 1
b100 3
1(
#30000
0(
#35000
1$
b11000110111111111111101110001101 "
b11000110111111111111101110001101 0
b11000110111111111111101110001101 .
b11000110110111111001100110001101 '
b11000110110111111001100110001101 +
b10000110101110010111101100001101 &
b10000110101110010111101100001101 *
b11 )
b11 ,
b11000110110111111001100110001101 2
b10000110101110010111101100001101 1
b11 3
1(
#40000
0(
#45000
b10001001111101111111001100010011 "
b10001001111101111111001100010011 0
b10001001111101111111001100010011 .
b10000000111100111110001100000001 '
b10000000111100111110001100000001 +
b1001001101110101001000010010 &
b1001001101110101001000010010 *
b10000000111100111110001100000001 2
b1001001101110101001000010010 1
1(
#50000
0(
#55000
b10111111101011111111110101111111 "
b10111111101011111111110101111111 0
b10111111101011111111110101111111 .
b10011110100011011100110100111101 '
b10011110100011011100110100111101 +
b10111011001000111111000101110110 &
b10111011001000111111000101110110 *
b10011110100011011100110100111101 2
b10111011001000111111000101110110 1
1(
#60000
0(
#65000
0$
b1 "
b1 0
b1 .
b11111100111111011110100111111001 '
b11111100111111011110100111111001 +
b11000110001011011111011110001100 &
b11000110001011011111011110001100 *
b101 )
b101 ,
b11111100111111011110100111111001 2
b11000110001011011111011110001100 1
b101 3
1(
#70000
0(
#75000
b110111111001000101011001101111 "
b110111111001000101011001101111 0
b110111111001000101011001101111 .
b1010101000100111101001010101010 '
b1010101000100111101001010101010 +
b1100010111101111000010011000101 &
b1100010111101111000010011000101 *
b100 )
b100 ,
b1010101000100111101001010101010 2
b1100010111101111000010011000101 1
b100 3
1(
#80000
0(
#85000
1!
b0 "
b0 0
b0 .
b1001001100101101011000010010 '
b1001001100101101011000010010 +
b111011110100100111001001110111 &
b111011110100100111001001110111 *
b101 )
b101 ,
b1001001100101101011000010010 2
b111011110100100111001001110111 1
b101 3
1(
#90000
0(
#95000
0!
b1 "
b1 0
b1 .
b1100111011101101001011011001110 '
b1100111011101101001011011001110 +
b11111001001100000110100111110010 &
b11111001001100000110100111110010 *
b1100111011101101001011011001110 2
b11111001001100000110100111110010 1
1(
#100000
0(
#105000
b100010010010000100100001000100 "
b100010010010000100100001000100 0
b100010010010000100100001000100 .
b10101110010110000100100101011100 '
b10101110010110000100100101011100 +
b1100010110010100100111011000101 &
b1100010110010100100111011000101 *
b10 )
b10 ,
b10101110010110000100100101011100 2
b1100010110010100100111011000101 1
b10 3
1(
#110000
0(
#115000
b110110101011110111111001101101 "
b110110101011110111111001101101 0
b110110101011110111111001101101 .
b110010101001110010011001100101 '
b110010101001110010011001100101 +
b10110101010110101100000101101 &
b10110101010110101100000101101 *
b11 )
b11 ,
b110010101001110010011001100101 2
b10110101010110101100000101101 1
b11 3
1(
#120000
0(
#125000
b1 "
b1 0
b1 .
b1000000001110110010001010000000 '
b1000000001110110010001010000000 +
b10000101011100111000011100001010 &
b10000101011100111000011100001010 *
b101 )
b101 ,
b1000000001110110010001010000000 2
b10000101011100111000011100001010 1
b101 3
1(
#130000
0(
#135000
1%
b100100010001010001001001000111 "
b100100010001010001001001000111 0
1-
b100100010001010001001001000111 .
b1001110110011001100110010011101 '
b1001110110011001100110010011101 +
b11010101011110000100010110101010 &
b11010101011110000100010110101010 *
b0 )
b0 ,
b1001110110011001100110010011101 2
b11010101011110000100010110101010 1
b0 3
1(
#140000
0(
#145000
0%
b1111001111111000000000011110 "
b1111001111111000000000011110 0
b1111001111111000000000011110 .
0-
b110101111000011100000001101 '
b110101111000011100000001101 +
b1001100000111011100000010011 &
b1001100000111011100000010011 *
b100 )
b100 ,
b110101111000011100000001101 2
b1001100000111011100000010011 1
b100 3
1(
#150000
0(
#155000
1#
b1001010111110011011001010010110 "
b1001010111110011011001010010110 0
1/
b1001010111110011011001010010110 .
b1101010101001100010101011010101 '
b1101010101001100010101011010101 +
b10110101100111111101110101101011 &
b10110101100111111101110101101011 *
b1 )
b1 ,
b1101010101001100010101011010101 2
b10110101100111111101110101101011 1
b1 3
1(
#160000
0(
#165000
0#
1$
b11011001101010011101011110110011 "
b11011001101010011101011110110011 0
b11011001101010011101011110110011 .
0/
b10001110111111111110100100011101 '
b10001110111111111110100100011101 +
b1010111010101100011111010101110 &
b1010111010101100011111010101110 *
b100 )
b100 ,
b10001110111111111110100100011101 2
b1010111010101100011111010101110 1
b100 3
1(
#170000
0(
#175000
b10010101100011010110110100101011 "
b10010101100011010110110100101011 0
b10010101100011010110110100101011 .
b10000101000010010110010100001010 '
b10000101000010010110010100001010 +
b10010001100001000100100100100011 &
b10010001100001000100100100100011 *
b11 )
b11 ,
b10000101000010010110010100001010 2
b10010001100001000100100100100011 1
b11 3
1(
#180000
0(
#185000
0$
b11000001000000000110000110000 "
b11000001000000000110000110000 0
b11000001000000000110000110000 .
b11111001011010001011110111110010 '
b11111001011010001011110111110010 +
b11110001100010100110000111100 &
b11110001100010100110000111100 *
b10 )
b10 ,
b11111001011010001011110111110010 2
b11110001100010100110000111100 1
b10 3
1(
#190000
0(
#195000
1$
b11001100100011111000011110011001 "
b11001100100011111000011110011001 0
b11001100100011111000011110011001 .
b1101100010010110011010011011000 '
b1101100010010110011010011011000 +
b10100000110001001011001101000001 &
b10100000110001001011001101000001 *
b100 )
b100 ,
b1101100010010110011010011011000 2
b10100000110001001011001101000001 1
b100 3
1(
#200000
0(
#205000
b10110001010011110001111101100010 "
b10110001010011110001111101100010 0
b10110001010011110001111101100010 .
b11110101110001010000110111101011 '
b11110101110001010000110111101011 +
b1000100100010100001001010001001 &
b1000100100010100001001010001001 *
b11110101110001010000110111101011 2
b1000100100010100001001010001001 1
1(
#210000
0(
#215000
1%
b10111010011000010000110101110100 "
b10111010011000010000110101110100 0
1-
b10111010011000010000110101110100 .
b11010111000101010001001110101110 '
b11010111000101010001001110101110 +
b11100011010010111111100111000110 &
b11100011010010111111100111000110 *
b0 )
b0 ,
b11010111000101010001001110101110 2
b11100011010010111111100111000110 1
b0 3
1(
#220000
0(
#225000
0%
0$
b101000001111001100000001010 "
b101000001111001100000001010 0
b101000001111001100000001010 .
0-
b101110101111001101000001011 '
b101110101111001101000001011 +
b10010101000011111101110100101010 &
b10010101000011111101110100101010 *
b10 )
b10 ,
b101110101111001101000001011 2
b10010101000011111101110100101010 1
b10 3
1(
#230000
0(
#235000
1$
b11100111111100100101010111001111 "
b11100111111100100101010111001111 0
b11100111111100100101010111001111 .
b10100111111100100101010101001111 '
b10100111111100100101010101001111 +
b11000010111100100100000110000101 &
b11000010111100100100000110000101 *
b11 )
b11 ,
b10100111111100100101010101001111 2
b11000010111100100100000110000101 1
b11 3
1(
#240000
0(
#245000
1#
0$
b1011101111000110000000010111100 "
b1011101111000110000000010111100 0
1/
b1011101111000110000000010111100 .
b111111001000110011001001111110 '
b111111001000110011001001111110 +
b10011101000001100011001100111010 &
b10011101000001100011001100111010 *
b1 )
b1 ,
b111111001000110011001001111110 2
b10011101000001100011001100111010 1
b1 3
1(
#250000
0(
#255000
0#
1!
b0 "
b0 0
b0 .
0/
b11101100100111000100101111011001 '
b11101100100111000100101111011001 +
b11111000110110011001101111110001 &
b11111000110110011001101111110001 *
b101 )
b101 ,
b11101100100111000100101111011001 2
b11111000110110011001101111110001 1
b101 3
1(
#260000
0(
#265000
1$
0!
b10000110001000010101000100001100 "
b10000110001000010101000100001100 0
b10000110001000010101000100001100 .
b11001111101000010101010110011111 '
b11001111101000010101010110011111 +
b10100110001101011111101101001100 &
b10100110001101011111101101001100 *
b10 )
b10 ,
b11001111101000010101010110011111 2
b10100110001101011111101101001100 1
b10 3
1(
#270000
0(
#275000
b10100000101000000100100101000001 "
b10100000101000000100100101000001 0
b10100000101000000100100101000001 .
b1011011110011010110000010110111 '
b1011011110011010110000010110111 +
b11111100011011011010100111111000 &
b11111100011011011010100111111000 *
b1 )
b1 ,
b1011011110011010110000010110111 2
b11111100011011011010100111111000 1
b1 3
1(
#280000
0(
#285000
0$
b101100011101010000000001 "
b101100011101010000000001 0
b101100011101010000000001 .
b101101110010111100000001011011 '
b101101110010111100000001011011 +
b101110011111011001010001011100 &
b101110011111011001010001011100 *
b101101110010111100000001011011 2
b101110011111011001010001011100 1
1(
#290000
0(
#295000
1%
1$
b10111100100010101111001101111001 "
b10111100100010101111001101111001 0
1-
b10111100100010101111001101111001 .
b1101000001000110011111011010000 '
b1101000001000110011111011010000 +
b100100101011100011001001001001 &
b100100101011100011001001001001 *
b1101000001000110011111011010000 2
b100100101011100011001001001001 1
1(
#300000
0(
#305000
0%
b11101011111001111111111111010111 "
b11101011111001111111111111010111 0
b11101011111001111111111111010111 .
0-
b11001011001000010010111110010110 '
b11001011001000010010111110010110 +
b101000110001111111110001010001 &
b101000110001111111110001010001 *
b11 )
b11 ,
b11001011001000010010111110010110 2
b101000110001111111110001010001 1
b11 3
1(
#310000
0(
#315000
0$
b1100000000001001100110011000000 "
b1100000000001001100110011000000 0
b1100000000001001100110011000000 .
b11100100010101111110110111001000 '
b11100100010101111110110111001000 +
b1100001001011001100111011000010 &
b1100001001011001100111011000010 *
b10 )
b10 ,
b11100100010101111110110111001000 2
b1100001001011001100111011000010 1
b10 3
1(
#320000
0(
#325000
1!
b0 "
b0 0
b0 .
b10001001000011001101101100010010 '
b10001001000011001101101100010010 +
b10011110111100101110110100111101 &
b10011110111100101110110100111101 *
b101 )
b101 ,
b10001001000011001101101100010010 2
b10011110111100101110110100111101 1
b101 3
1(
#330000
0(
#335000
1$
0!
b10010100110000011000000100101001 "
b10010100110000011000000100101001 0
b10010100110000011000000100101001 .
b10011100110110011110011100111001 '
b10011100110110011110011100111001 +
b10110110111001011000000101101101 &
b10110110111001011000000101101101 *
b10 )
b10 ,
b10011100110110011110011100111001 2
b10110110111001011000000101101101 1
b10 3
1(
#340000
0(
#345000
0$
1!
b0 "
b0 0
b0 .
b11000010110110010010111110000101 '
b11000010110110010010111110000101 +
b1101001111010111111011011010011 &
b1101001111010111111011011010011 *
b101 )
b101 ,
b11000010110110010010111110000101 2
b1101001111010111111011011010011 1
b101 3
1(
#350000
0(
#355000
1#
1%
0!
b1010010011001011010010010100100 "
b1010010011001011010010010100100 0
1/
1-
b1010010011001011010010010100100 .
b10100100100010110100101101001001 '
b10100100100010110100101101001001 +
b10101101110110100101100101011011 &
b10101101110110100101100101011011 *
b0 )
b0 ,
b10100100100010110100101101001001 2
b10101101110110100101100101011011 1
b0 3
1(
#360000
0(
#365000
0#
0%
1$
b10111101000111011110111101111010 "
b10111101000111011110111101111010 0
b10111101000111011110111101111010 .
0/
0-
b10101100000101010110001101011000 '
b10101100000101010110001101011000 +
b10010101000011001010111100101010 &
b10010101000011001010111100101010 *
b11 )
b11 ,
b10101100000101010110001101011000 2
b10010101000011001010111100101010 1
b11 3
1(
#370000
0(
#375000
0$
b1000110000010100000000010001100 "
b1000110000010100000000010001100 0
b1000110000010100000000010001100 .
b1001110001011111111001010011100 '
b1001110001011111111001010011100 +
b1000111000110100000110010001110 &
b1000111000110100000110010001110 *
b10 )
b10 ,
b1001110001011111111001010011100 2
b1000111000110100000110010001110 1
b10 3
1(
#380000
0(
#385000
1$
b10101010111010111010101101010101 "
b10101010111010111010101101010101 0
b10101010111010111010101101010101 .
b10111001100101100001011101110011 '
b10111001100101100001011101110011 +
b10011011111011011110000100110 &
b10011011111011011110000100110 *
b100 )
b100 ,
b10111001100101100001011101110011 2
b10011011111011011110000100110 1
b100 3
1(
#390000
0(
#395000
0$
b1 "
b1 0
b1 .
b1011001110100101001001010110011 '
b1011001110100101001001010110011 +
b10111100110011010100000101111 &
b10111100110011010100000101111 *
b101 )
b101 ,
b1011001110100101001001010110011 2
b10111100110011010100000101111 1
b101 3
1(
#400000
0(
#405000
1$
b11111011111110011111110111110111 "
b11111011111110011111110111110111 0
b11111011111110011111110111110111 .
b11111011111110001111110111110111 '
b11111011111110001111110111110111 +
b10100010001010010000110101000100 &
b10100010001010010000110101000100 *
b11 )
b11 ,
b11111011111110001111110111110111 2
b10100010001010010000110101000100 1
b11 3
1(
#410000
0(
#415000
b11111111001010011101101111111110 "
b11111111001010011101101111111110 0
b11111111001010011101101111111110 .
b10101101001010001101101101011010 '
b10101101001010001101101101011010 +
b1110011000010010001101011100110 &
b1110011000010010001101011100110 *
b10101101001010001101101101011010 2
b1110011000010010001101011100110 1
1(
#420000
0(
#425000
0$
b1001001011110111011000010011 "
b1001001011110111011000010011 0
b1001001011110111011000010011 .
b1101101010100110110110011011010 '
b1101101010100110110110011011010 +
b1110110100000101110001011101101 &
b1110110100000101110001011101101 *
b1 )
b1 ,
b1101101010100110110110011011010 2
b1110110100000101110001011101101 1
b1 3
1(
#430000
0(
#435000
b1111111101111101111011011111111 "
b1111111101111101111011011111111 0
b1111111101111101111011011111111 .
b1101111101111101001010011011111 '
b1101111101111101001010011011111 +
b1011010100010101110001010110101 &
b1011010100010101110001010110101 *
b11 )
b11 ,
b1101111101111101001010011011111 2
b1011010100010101110001010110101 1
b11 3
1(
#440000
0(
#445000
b1 "
b1 0
b1 .
b1101000011101000000110011010000 '
b1101000011101000000110011010000 +
b10100010001100011111111101000100 &
b10100010001100011111111101000100 *
b101 )
b101 ,
b1101000011101000000110011010000 2
b10100010001100011111111101000100 1
b101 3
1(
#450000
0(
#455000
b1010010100110010110001010100101 "
b1010010100110010110001010100101 0
b1010010100110010110001010100101 .
b10000111011011111100111100001110 '
b10000111011011111100111100001110 +
b11010101111101101010110110101011 &
b11010101111101101010110110101011 *
b100 )
b100 ,
b10000111011011111100111100001110 2
b11010101111101101010110110101011 1
b100 3
1(
#460000
0(
#465000
b110011100000011100111001100111 "
b110011100000011100111001100111 0
b110011100000011100111001100111 .
b1111110110111110111001011111101 '
b1111110110111110111001011111101 +
b1001101010111101011110010011010 &
b1001101010111101011110010011010 *
b1111110110111110111001011111101 2
b1001101010111101011110010011010 1
1(
#470000
0(
#475000
b11100101010000010000001000 "
b11100101010000010000001000 0
b11100101010000010000001000 .
b10100111011110011110100101001110 '
b10100111011110011110100101001110 +
b10101011000011101110110101010110 &
b10101011000011101110110101010110 *
b1 )
b1 ,
b10100111011110011110100101001110 2
b10101011000011101110110101010110 1
b1 3
1(
#480000
0(
#485000
1$
b11011111011111111011110110111110 "
b11011111011111111011110110111110 0
b11011111011111111011110110111110 .
b11011011011011111011100110110110 '
b11011011011011111011100110110110 +
b101001100010011010000001010 &
b101001100010011010000001010 *
b11 )
b11 ,
b11011011011011111011100110110110 2
b101001100010011010000001010 1
b11 3
1(
#490000
0(
#495000
0$
b11100000000011000010000111000 "
b11100000000011000010000111000 0
b11100000000011000010000111000 .
b1011100001010111100010010111000 '
b1011100001010111100010010111000 +
b10111100110100011000011101111001 &
b10111100110100011000011101111001 *
b10 )
b10 ,
b1011100001010111100010010111000 2
b10111100110100011000011101111001 1
b10 3
1(
#500000
0(
#505000
1$
b11001100000001011000100110010111 "
b11001100000001011000100110010111 0
b11001100000001011000100110010111 .
b10001111110010110000000100 '
b10001111110010110000000100 +
b11001001110001100101110110010011 &
b11001001110001100101110110010011 *
b0 )
b0 ,
b10001111110010110000000100 2
b11001001110001100101110110010011 1
b0 3
1(
#510000
0(
#515000
0$
b1 "
b1 0
b1 .
b100110111111001101111001001101 '
b100110111111001101111001001101 +
b11101101110010110110100111011011 &
b11101101110010110110100111011011 *
b101 )
b101 ,
b100110111111001101111001001101 2
b11101101110010110110100111011011 1
b101 3
1(
#520000
0(
#525000
b1 .
b111011010001011110001001110110 '
b111011010001011110001001110110 +
b110110101001000010011001101101 &
b110110101001000010011001101101 *
b111011010001011110001001110110 2
b110110101001000010011001101101 1
1(
#530000
0(
#535000
1$
b11001010000100110010000110010100 "
b11001010000100110010000110010100 0
b11001010000100110010000110010100 .
b11001010100100110111000110010101 '
b11001010100100110111000110010101 +
b11011011000101110010110110110110 &
b11011011000101110010110110110110 *
b10 )
b10 ,
b11001010100100110111000110010101 2
b11011011000101110010110110110110 1
b10 3
1(
#540000
0(
#545000
1#
1%
0$
b1111110010001101111110011111011 "
b1111110010001101111110011111011 0
1/
1-
b1111110010001101111110011111011 .
b11111011110100100110000111110111 '
b11111011110100100110000111110111 +
b10000010011101001001101100000100 &
b10000010011101001001101100000100 *
b0 )
b0 ,
b11111011110100100110000111110111 2
b10000010011101001001101100000100 1
b0 3
1(
#550000
0(
#555000
0#
0%
1$
b11011110011011111011111110111100 "
b11011110011011111011111110111100 0
b11011110011011111011111110111100 .
0/
0-
b11000100000000011000110110001000 '
b11000100000000011000110110001000 +
b1011010011011101011101010110100 &
b1011010011011101011101010110100 *
b11 )
b11 ,
b11000100000000011000110110001000 2
b1011010011011101011101010110100 1
b11 3
1(
#560000
0(
#565000
0$
b1110101010101010011010011101010 "
b1110101010101010011010011101010 0
b1110101010101010011010011101010 .
b1100011110001010011000011000111 '
b1100011110001010011000011000111 +
b10110100100000000010000101101 &
b10110100100000000010000101101 *
b100 )
b100 ,
b1100011110001010011000011000111 2
b10110100100000000010000101101 1
b100 3
1(
#570000
0(
#575000
b100010000010100010000001000 "
b100010000010100010000001000 0
b100010000010100010000001000 .
b10001110010000010100010100011100 '
b10001110010000010100010100011100 +
b100011101111110010000001000 &
b100011101111110010000001000 *
b10 )
b10 ,
b10001110010000010100010100011100 2
b100011101111110010000001000 1
b10 3
1(
#580000
0(
#585000
1$
b10000110011001100111011100001101 "
b10000110011001100111011100001101 0
b10000110011001100111011100001101 .
b1110001101111001000000011100 '
b1110001101111001000000011100 +
b10010100100111100000011100101001 &
b10010100100111100000011100101001 *
b1 )
b1 ,
b1110001101111001000000011100 2
b10010100100111100000011100101001 1
b1 3
1(
#590000
0(
#595000
0$
b1100001101000000000000011000 "
b1100001101000000000000011000 0
b1100001101000000000000011000 .
b11110101101111100011000111101 '
b11110101101111100011000111101 +
b1101101001101000000100011011010 &
b1101101001101000000100011011010 *
b10 )
b10 ,
b11110101101111100011000111101 2
b1101101001101000000100011011010 1
b10 3
1(
#600000
0(
#605000
b1101000001100000000000011 "
b1101000001100000000000011 0
b1101000001100000000000011 .
b111001111101010000010001110011 '
b111001111101010000010001110011 +
b111000010101011100010001110000 &
b111000010101011100010001110000 *
b100 )
b100 ,
b111001111101010000010001110011 2
b111000010101011100010001110000 1
b100 3
1(
#610000
0(
#615000
b1010010011111011100101010100100 "
b1010010011111011100101010100100 0
b1010010011111011100101010100100 .
b11111101010001110111100111111010 '
b11111101010001110111100111111010 +
b10101111001110101011001101011110 &
b10101111001110101011001101011110 *
b11111101010001110111100111111010 2
b10101111001110101011001101011110 1
1(
#620000
0(
#625000
b1011101111101001111011010111011 "
b1011101111101001111011010111011 0
b1011101111101001111011010111011 .
b1011100111100000000000010111001 '
b1011100111100000000000010111001 +
b1101001001001111011000011010 &
b1101001001001111011000011010 *
b11 )
b11 ,
b1011100111100000000000010111001 2
b1101001001001111011000011010 1
b11 3
1(
#630000
0(
#635000
1%
1$
b11101010111011100001010111010110 "
b11101010111011100001010111010110 0
1-
b11101010111011100001010111010110 .
b11100000001110010010000111000000 '
b11100000001110010010000111000000 +
b11001011001001110011011110010110 &
b11001011001001110011011110010110 *
b1 )
b1 ,
b11100000001110010010000111000000 2
b11001011001001110011011110010110 1
b1 3
1(
#640000
0(
#645000
0$
b11001110111111001111000110011 "
b11001110111111001111000110011 0
b11001110111111001111000110011 .
1-
b10111110100110011000001101111101 '
b10111110100110011000001101111101 +
b1011011010001100001101010110110 &
b1011011010001100001101010110110 *
b0 )
b0 ,
b10111110100110011000001101111101 2
b1011011010001100001101010110110 1
b0 3
1(
#650000
0(
#655000
0%
b1111111011000101010100011111110 "
b1111111011000101010100011111110 0
b1111111011000101010100011111110 .
0-
b10111100000000111111111101111000 '
b10111100000000111111111101111000 +
b11000011011000010101011110000110 &
b11000011011000010101011110000110 *
b100 )
b100 ,
b10111100000000111111111101111000 2
b11000011011000010101011110000110 1
b100 3
1(
#660000
0(
#665000
b1010010011100011011000010100 "
b1010010011100011011000010100 0
b1010010011100011011000010100 .
b1100111110000111011011011001111 '
b1100111110000111011011011001111 +
b1101101100011011000000011011011 &
b1101101100011011000000011011011 *
b1100111110000111011011011001111 2
b1101101100011011000000011011011 1
1(
#670000
0(
#675000
b1001100011010111111011010011001 "
b1001100011010111111011010011001 0
b1001100011010111111011010011001 .
b110000101111001110111001100001 '
b110000101111001110111001100001 +
b1111101001010001110010011111010 &
b1111101001010001110010011111010 *
b1 )
b1 ,
b110000101111001110111001100001 2
b1111101001010001110010011111010 1
b1 3
1(
#680000
0(
#685000
1#
1%
1$
b10001101011111011110011100011011 "
b10001101011111011110011100011011 0
1/
1-
b10001101011111011110011100011011 .
b11000011011101111001000110000110 '
b11000011011101111001000110000110 +
b1010000111101010111100010100001 &
b1010000111101010111100010100001 *
b11000011011101111001000110000110 2
b1010000111101010111100010100001 1
1(
#690000
0(
#695000
0#
0$
b10101010000001110001000101010 "
b10101010000001110001000101010 0
b10101010000001110001000101010 .
0/
1-
b11010101101001000100000110101 '
b11010101101001000100000110101 +
b11111010100011000101100111110101 &
b11111010100011000101100111110101 *
b0 )
b0 ,
b11010101101001000100000110101 2
b11111010100011000101100111110101 1
b0 3
1(
#700000
0(
#705000
0%
b1 "
b1 0
b1 .
0-
b1100010111001010111010011000101 '
b1100010111001010111010011000101 +
b11100000101100010111010111000001 &
b11100000101100010111010111000001 *
b101 )
b101 ,
b1100010111001010111010011000101 2
b11100000101100010111010111000001 1
b101 3
1(
#710000
0(
#715000
1$
b10011100001111100011100100111000 "
b10011100001111100011100100111000 0
b10011100001111100011100100111000 .
b111001100011000100001001110011 '
b111001100011000100001001110011 +
b10100101101100100111101101001011 &
b10100101101100100111101101001011 *
b100 )
b100 ,
b111001100011000100001001110011 2
b10100101101100100111101101001011 1
b100 3
1(
#720000
0(
#725000
b11101100101010001110011111011000 "
b11101100101010001110011111011000 0
b11101100101010001110011111011000 .
b10100111010110001101000101001110 '
b10100111010110001101000101001110 +
b1000101010100000001011010001010 &
b1000101010100000001011010001010 *
b0 )
b0 ,
b10100111010110001101000101001110 2
b1000101010100000001011010001010 1
b0 3
1(
#730000
0(
#735000
0$
b1010000100010101000110010100001 "
b1010000100010101000110010100001 0
b1010000100010101000110010100001 .
b1010000110010101000110010100001 '
b1010000110010101000110010100001 +
b11010100100111101111110110101001 &
b11010100100111101111110110101001 *
b10 )
b10 ,
b1010000110010101000110010100001 2
b11010100100111101111110110101001 1
b10 3
1(
#740000
0(
#745000
1#
1$
b11000011000010110010011110000101 "
b11000011000010110010011110000101 0
1/
b11000011000010110010011110000101 .
b1001111110101101100000010011111 '
b1001111110101101100000010011111 +
b1110011001101000110011011100110 &
b1110011001101000110011011100110 *
b0 )
b0 ,
b1001111110101101100000010011111 2
b1110011001101000110011011100110 1
b0 3
1(
#750000
0(
#755000
0#
0$
b100000100000001010000001000 "
b100000100000001010000001000 0
b100000100000001010000001000 .
0/
b1000110101101011111010010001101 '
b1000110101101011111010010001101 +
b10010101010110100001110100101010 &
b10010101010110100001110100101010 *
b10 )
b10 ,
b1000110101101011111010010001101 2
b10010101010110100001110100101010 1
b10 3
1(
#760000
0(
#765000
b11100010011011010000000111000 "
b11100010011011010000000111000 0
b11100010011011010000000111000 .
b111100110011111010100001111001 '
b111100110011111010100001111001 +
b11100011011011110011000111000 &
b11100011011011110011000111000 *
b111100110011111010100001111001 2
b11100011011011110011000111000 1
1(
#770000
0(
#775000
1$
b10000001001000110100000100000010 "
b10000001001000110100000100000010 0
b10000001001000110100000100000010 .
b10001001111111110100000100010011 '
b10001001111111110100000100010011 +
b11100101001000110100010111001010 &
b11100101001000110100010111001010 *
b10001001111111110100000100010011 2
b11100101001000110100010111001010 1
1(
#780000
0(
#785000
1#
1%
b10001000101010111101000100010001 "
b10001000101010111101000100010001 0
1/
1-
b10001000101010111101000100010001 .
b11011011000010111101110110110110 '
b11011011000010111101110110110110 +
b1100011101101111010111011000111 &
b1100011101101111010111011000111 *
b1 )
b1 ,
b11011011000010111101110110110110 2
b1100011101101111010111011000111 1
b1 3
1(
#790000
0(
#795000
0#
0%
b11000000000000101000000110000000 "
b11000000000000101000000110000000 0
b11000000000000101000000110000000 .
0/
0-
b11011100100000101001010110111001 '
b11011100100000101001010110111001 +
b11100010000101101010101111000100 &
b11100010000101101010101111000100 *
b10 )
b10 ,
b11011100100000101001010110111001 2
b11100010000101101010101111000100 1
b10 3
1(
#800000
0(
#805000
0$
b11010001000100001101000110100 "
b11010001000100001101000110100 0
b11010001000100001101000110100 .
b10111111101110110011101101111111 '
b10111111101110110011101101111111 +
b1011010001001101001101010110100 &
b1011010001001101001101010110100 *
b10111111101110110011101101111111 2
b1011010001001101001101010110100 1
1(
#810000
0(
#815000
1%
b1110110100101011000101011101100 "
b1110110100101011000101011101100 0
1-
b1110110100101011000101011101100 .
b1111001001001111001010011110010 '
b1111001001001111001010011110010 +
b11111101011011011111010111111010 &
b11111101011011011111010111111010 *
b0 )
b0 ,
b1111001001001111001010011110010 2
b11111101011011011111010111111010 1
b0 3
1(
#820000
0(
#825000
0%
b1000010010011100100110010000100 "
b1000010010011100100110010000100 0
b1000010010011100100110010000100 .
0-
b11000010010011111100110110000100 '
b11000010010011111100110110000100 +
b1011110110011100101111010111101 &
b1011110110011100101111010111101 *
b10 )
b10 ,
b11000010010011111100110110000100 2
b1011110110011100101111010111101 1
b10 3
1(
#830000
0(
#835000
1%
1$
b10111001111011000100100101110011 "
b10111001111011000100100101110011 0
1-
b10111001111011000100100101110011 .
b11010100101010000111100110101001 '
b11010100101010000111100110101001 +
b11100101010000111100111111001010 &
b11100101010000111100111111001010 *
b0 )
b0 ,
b11010100101010000111100110101001 2
b11100101010000111100111111001010 1
b0 3
1(
#840000
0(
#845000
0%
b11111111111011111110101111111111 "
b11111111111011111110101111111111 0
b11111111111011111110101111111111 .
0-
b1111101100010110110101011111011 '
b1111101100010110110101011111011 +
b11000111011001011010100110001110 &
b11000111011001011010100110001110 *
b11 )
b11 ,
b1111101100010110110101011111011 2
b11000111011001011010100110001110 1
b11 3
1(
#850000
0(
